pylibversion/__init__.py
pylibversion/version_util.py
pylibversion-0.1.0.dist-info/LICENSE
pylibversion-0.1.0.dist-info/METADATA
pylibversion-0.1.0.dist-info/WHEEL
pylibversion-0.1.0.dist-info/top_level.txt
pylibversion-0.1.0.dist-info/RECORD
