Metadata-Version: 2.1
Name: pylibversion
Version: 0.1.0
Summary: A library to help manage python library versions
Home-page: https://github.com/dbradf/pylibversion
Author: David Bradford
Author-email: david.bradford@mongodb.com
License: Apache License, Version 2.0
Platform: UNKNOWN
Classifier: Intended Audience :: Developers
Classifier: Operating System :: Unix
Classifier: Operating System :: POSIX
Classifier: Operating System :: Microsoft :: Windows
Classifier: Programming Language :: Python
Classifier: Programming Language :: Python :: 3
Classifier: Programming Language :: Python :: Implementation :: CPython
Classifier: Programming Language :: Python :: Implementation :: PyPy
Requires-Dist: requests (~=2.0)
